[{"index":"2011","subjectCode":"CTE 493","subjectName":"Research Statistics_9/19/2016","link":"https://dl.lib.kmutt.ac.th/repository/loadfile.php?obj_id=4138","callNumber":"","year":"2559","semester":"1","examType":"Mid-Term"},{"index":"2012","subjectCode":"CTE 493","subjectName":"Research Statistics(ผศ.ดร.สนิท วงษา)","link":"https://dl.lib.kmutt.ac.th/repository/loadfile.php?obj_id=752","callNumber":"","year":"2557","semester":"2","examType":"Mid-Term"},{"index":"2013","subjectCode":"CTE327, CTE 426","subjectName":"Steel and Timber Design, Timber and Steel Design(ครุโยธาปี 3, 4)","link":null,"callNumber":"S 2550","year":"2550","semester":"2","examType":"Mid-Term"},{"index":"2014","subjectCode":"CTE451/ CVT 333","subjectName":"Highway Engineering / Highway","link":"https://dl.lib.kmutt.ac.th/repository/loadfile.php?obj_id=4586","callNumber":"","year":"2559","semester":"2","examType":"Final"},{"index":"2015","subjectCode":"CVE 100","subjectName":"Computer Programming for Civil Engineering_5 Mar. 2019","link":"https://dl.lib.kmutt.ac.th/repository/loadfile.php?obj_id=6354","callNumber":"","year":"2561","semester":"2","examType":"Mid-Term"},{"index":"2016","subjectCode":"CVE 100","subjectName":"Computer Programming for Civil Engineering_15 May 2019","link":"https://dl.lib.kmutt.ac.th/repository/loadfile.php?obj_id=6418","callNumber":"","year":"2561","semester":"2","examType":"Final"},{"index":"2017","subjectCode":"CVE 100","subjectName":"Computer Programming for Civil Engineering_29 กันยายน 2560","link":"https://dl.lib.kmutt.ac.th/repository/loadfile.php?obj_id=5924","callNumber":"","year":"2560","semester":"1","examType":"Mid-Term"},{"index":"2018","subjectCode":"CVE 100","subjectName":"Computer Programming for Civil Engineers_29 September 2017","link":"https://dl.lib.kmutt.ac.th/repository/loadfile.php?obj_id=5925","callNumber":"","year":"2560","semester":"1","examType":"Mid-Term"},{"index":"2019","subjectCode":"CVE 100","subjectName":"Computer Programming for Civil Engineering_12/4/2017","link":"https://dl.lib.kmutt.ac.th/repository/loadfile.php?obj_id=5997","callNumber":"","year":"2560","semester":"1","examType":"Final"},{"index":"2020","subjectCode":"CVE 100","subjectName":"Computer Programming for Civil Engineers_12/4/2017","link":"https://dl.lib.kmutt.ac.th/repository/loadfile.php?obj_id=5998","callNumber":"","year":"2560","semester":"1","examType":"Final"}]