[{"index":"7981","subjectCode":"MTH 363","subjectName":"Numerical Methods I   27 ธ.ค.2550","link":"https://dl.lib.kmutt.ac.th/repository/loadfile.php?obj_id=4904","callNumber":"","year":"2550","semester":"2","examType":"Mid-Term"},{"index":"7982","subjectCode":"MTH 363","subjectName":"Numerical methods I   14 ส.ค.2550","link":"https://dl.lib.kmutt.ac.th/repository/loadfile.php?obj_id=3602","callNumber":"N-O 2550","year":"2550","semester":"1","examType":"Mid-Term"},{"index":"7983","subjectCode":"MTH 363","subjectName":"Numerical Methods I   15 ต.ค.2550.","link":"https://dl.lib.kmutt.ac.th/repository/loadfile.php?obj_id=3998","callNumber":"N-O 2550","year":"2550","semester":"1","examType":"Final"},{"index":"7984","subjectCode":"MTH 363","subjectName":"Numerical Methods","link":null,"callNumber":"N-O 2549","year":"2549","semester":"1","examType":"Mid-Term,Final"},{"index":"7985","subjectCode":"MTH 363","subjectName":"Numerical Methods","link":null,"callNumber":"N-O 2548","year":"2548","semester":"1","examType":"Mid-Term,Final"},{"index":"7986","subjectCode":"MTH 363","subjectName":"Numerical Methods","link":null,"callNumber":"N-O 2547","year":"2547","semester":"1","examType":"Mid-Term,Final"},{"index":"7987","subjectCode":"MTH 363","subjectName":"Numerical Methods","link":null,"callNumber":"N-O 2546","year":"2546","semester":"1","examType":"Mid-Term,Final"},{"index":"7988","subjectCode":"MTH 363","subjectName":"Numerical Methods I","link":null,"callNumber":"N-O 2545","year":"2545","semester":"1","examType":"Mid-Term"},{"index":"7989","subjectCode":"MTH 363","subjectName":"Numerical Methods I","link":null,"callNumber":"N-O 2544","year":"2544","semester":"1","examType":"Mid-Term,Final"},{"index":"7990","subjectCode":"MTH 363","subjectName":"Numerical Methods I","link":null,"callNumber":"N-O 2543","year":"2543","semester":"1","examType":"Mid-Term,Final"}]