[{"index":"4341","subjectCode":"ENE 334","subjectName":"Microprocessors","link":null,"callNumber":"ME-MU 2547","year":"2547","semester":"1","examType":"Mid-Term"},{"index":"4342","subjectCode":"ENE 334","subjectName":"Microprocessor-Based Design System","link":null,"callNumber":"ME-MU 2546","year":"2546","semester":"2","examType":"Final"},{"index":"4343","subjectCode":"ENE 334","subjectName":"Microprocessors","link":null,"callNumber":"ME-MU 2546","year":"2546","semester":"1","examType":"Mid-Term,Final"},{"index":"4344","subjectCode":"ENE 334","subjectName":"Microproccessors","link":null,"callNumber":"ME-MU 2545","year":"2545","semester":"1","examType":"Mid-Term,Final"},{"index":"4345","subjectCode":"ENE 334 (MCE 323","subjectName":"Microprocessor (อ.ประสิทธิ์ นางทิน)","link":null,"callNumber":"ME-MU 2549","year":"2549","semester":"1","examType":"Final"},{"index":"4346","subjectCode":"ENE 335","subjectName":"Digital Circuits & Microprocessors Lab","link":null,"callNumber":"D 2546","year":"2546","semester":"2","examType":"Final"},{"index":"4347","subjectCode":"ENE 341","subjectName":"ระบบควบคุมเชิงเส้น_7 มี.ค.62","link":"https://dl.lib.kmutt.ac.th/repository/loadfile.php?obj_id=6370","callNumber":"","year":"2561","semester":"2","examType":"Mid-Term"},{"index":"4348","subjectCode":"ENE 341","subjectName":"ระบบควบคุมเชิงเส้น_18 พฤษภาคม 2561","link":"https://dl.lib.kmutt.ac.th/repository/loadfile.php?obj_id=6192","callNumber":"","year":"2560","semester":"2","examType":"Final"},{"index":"4349","subjectCode":"ENE 341","subjectName":"ระบบควบคุมเชิงเส้น_8 มีนาคม 2561","link":"https://dl.lib.kmutt.ac.th/repository/loadfile.php?obj_id=6111","callNumber":"","year":"2560","semester":"2","examType":"Mid-Term"},{"index":"4350","subjectCode":"ENE 341","subjectName":"ระบบควบคุมเชิงเส้น","link":"https://dl.lib.kmutt.ac.th/repository/loadfile.php?obj_id=4489","callNumber":"","year":"2559","semester":"2","examType":"Mid-Term"}]