[{"index":"4071","subjectCode":"ENE 203","subjectName":"Electrical & Electronics Engineering Math","link":null,"callNumber":"EC-EL 2543","year":"2543","semester":"2","examType":"Mid-Term,Final"},{"index":"4072","subjectCode":"ENE 203","subjectName":"Electrical and Electronics Engineering Mathematics","link":null,"callNumber":"EDU-ELE 2542","year":"2542","semester":"2","examType":"Mid-Term"},{"index":"4073","subjectCode":"ENE 204","subjectName":"Electrical and Electronics Drawing","link":null,"callNumber":"ED-EL 2546","year":"2546","semester":"1","examType":"Final"},{"index":"4074","subjectCode":"ENE 204","subjectName":"Electrical and Electronics Drawing","link":null,"callNumber":"ED-EL 2545","year":"2545","semester":"1","examType":"Final"},{"index":"4075","subjectCode":"ENE 204","subjectName":"Electrical and Electronics Drawing","link":null,"callNumber":"ED-EL 2544","year":"2544","semester":"1","examType":"Final"},{"index":"4076","subjectCode":"ENE 204","subjectName":"Electrical and Electronics Drawing","link":null,"callNumber":"EC-EL 2543","year":"2543","semester":"1","examType":"Final"},{"index":"4077","subjectCode":"ENE 204","subjectName":"Electrical and Electronics Drawing","link":null,"callNumber":"EDU-ELE 2542","year":"2542","semester":"1","examType":"Final"},{"index":"4078","subjectCode":"ENE 205","subjectName":"Electronic Engineering Practice","link":"https://dl.lib.kmutt.ac.th/repository/loadfile.php?obj_id=190","callNumber":"EL 2555","year":"2555","semester":"1","examType":"Final"},{"index":"4079","subjectCode":"ENE 205","subjectName":"Electronic Engineering Practices  7 ต.ค.2552","link":"https://dl.lib.kmutt.ac.th/repository/loadfile.php?obj_id=3222","callNumber":"EL 2552","year":"2552","semester":"1","examType":"Final"},{"index":"4080","subjectCode":"ENE 205","subjectName":"Electronic Engineering Practice  8 ต.ค.2551","link":"https://dl.lib.kmutt.ac.th/repository/loadfile.php?obj_id=3837","callNumber":"EL 2551","year":"2551","semester":"1","examType":"Final"}]