[{"index":"6231","subjectCode":"MEE 213","subjectName":"Mechanics of Solids (Mechanical engineering, Tools and materials eng., Production eng.)","link":"https://dl.lib.kmutt.ac.th/repository/loadfile.php?obj_id=694","callNumber":"ME-MU 2557","year":"2557","semester":"2","examType":"Mid-Term"},{"index":"6232","subjectCode":"MEE 213","subjectName":"Mechanics of Solids (Mechanical engineering, Tools and materials eng., Production eng.)","link":"https://dl.lib.kmutt.ac.th/repository/loadfile.php?obj_id=857","callNumber":"ME-MU 2557","year":"2557","semester":"2","examType":"Final"},{"index":"6233","subjectCode":"MEE 213","subjectName":"Mechanics of Solids (Mechanical engineering, Tools and materials eng., Production eng.)","link":"https://dl.lib.kmutt.ac.th/repository/loadfile.php?obj_id=1030","callNumber":"ME-MU 2557","year":"2557","semester":"1","examType":"Final"},{"index":"6234","subjectCode":"MEE 213","subjectName":"Mechanics of Solids  (Production Engineering)","link":"https://dl.lib.kmutt.ac.th/repository/loadfile.php?obj_id=12","callNumber":"ME-MU 2556","year":"2556","semester":"1","examType":"Mid-Term"},{"index":"6235","subjectCode":"MEE 213","subjectName":"Mechanics of Solids I (Production Eng., Tools and Materials Eng. and Mechanical Eng.)_24 Feb 2012","link":"https://dl.lib.kmutt.ac.th/repository/loadfile.php?obj_id=2111","callNumber":"ME-MO 2554","year":"2554","semester":"2","examType":"Med-Term"},{"index":"6236","subjectCode":"MEE 213","subjectName":"Mechanics of Solids (Mechanical engineering, Tools and materials eng., Production eng.)","link":"https://dl.lib.kmutt.ac.th/repository/loadfile.php?obj_id=2423","callNumber":"ME-MO 2554","year":"2554","semester":"2","examType":"Final"},{"index":"6237","subjectCode":"MEE 213","subjectName":"Mechanics of Solids I (Production Eng., Tools and Materials Eng. and chemical Eng.)/26 Sep 2011","link":"https://dl.lib.kmutt.ac.th/repository/loadfile.php?obj_id=1732","callNumber":"ME-MO 2554","year":"2554","semester":"1","examType":"Final"},{"index":"6238","subjectCode":"MEE 213","subjectName":"Mechanics of Solids 21 December 2010","link":"https://dl.lib.kmutt.ac.th/repository/loadfile.php?obj_id=5654","callNumber":"","year":"2553","semester":"2","examType":"Mid-Term"},{"index":"6239","subjectCode":"MEE 213","subjectName":"Mechanics of Solids  1 Mar 2011","link":"https://dl.lib.kmutt.ac.th/repository/loadfile.php?obj_id=5852","callNumber":"ME-MU 2553","year":"2553","semester":"2","examType":"Final"},{"index":"6240","subjectCode":"MEE 213","subjectName":"Mechanics of Solids 19 July 2010","link":"https://dl.lib.kmutt.ac.th/repository/loadfile.php?obj_id=2902","callNumber":"ME-MU 2553","year":"2553","semester":"1","examType":"Mid-Term"}]