[{"index":"1931","subjectCode":"CTE 432","subjectName":"Hydraulics Engineering","link":null,"callNumber":"G-H 2549","year":"2549","semester":"1","examType":"Mid-Term,Final"},{"index":"1932","subjectCode":"CTE 432","subjectName":"Hydraulic Engineering","link":null,"callNumber":"G-H 2548","year":"2548","semester":"1","examType":"Mid-Term,Final"},{"index":"1933","subjectCode":"CTE 432","subjectName":"Hydraulic Engineering","link":null,"callNumber":"G-H 2547","year":"2547","semester":"1","examType":"Mid-Term,Final"},{"index":"1934","subjectCode":"CTE 432","subjectName":"Hydraulic Engineering","link":null,"callNumber":"G-H 2546","year":"2546","semester":"1","examType":"Final"},{"index":"1935","subjectCode":"CTE 432","subjectName":"Hydraulic Engineering","link":null,"callNumber":"G-H 2545","year":"2545","semester":"1","examType":"Mid-Term,Final"},{"index":"1936","subjectCode":"CTE 432","subjectName":"Hydraulic Engineering","link":null,"callNumber":"G-H 2544","year":"2544","semester":"1","examType":"Mid-Term"},{"index":"1937","subjectCode":"CTE 432","subjectName":"Hydraulic Engineering","link":null,"callNumber":"G-H 2543","year":"2543","semester":"1","examType":"Mid-Term"},{"index":"1938","subjectCode":"CTE 435","subjectName":"Hydrology  7 ต.ค.2551","link":"https://dl.lib.kmutt.ac.th/repository/loadfile.php?obj_id=3792","callNumber":"G-H 2551","year":"2551","semester":"1","examType":"Final"},{"index":"1939","subjectCode":"CTE 435","subjectName":"CTE 435 Hydrology  29 ก.ค.2551","link":"https://dl.lib.kmutt.ac.th/repository/loadfile.php?obj_id=3429","callNumber":"G-H 2551","year":"2551","semester":"1","examType":"Mid-Term"},{"index":"1940","subjectCode":"CTE 443","subjectName":"Foundation Engineering(ผศ.ดร.กิติเดช สันติชัยอนันต์)","link":"https://dl.lib.kmutt.ac.th/repository/loadfile.php?obj_id=1120","callNumber":"F 2557","year":"2557","semester":"1","examType":"Mid-Term"}]