[{"index":"1441","subjectCode":"CSS 223","subjectName":"Data Structures/27 ก.ย. 2554","link":"https://dl.lib.kmutt.ac.th/repository/loadfile.php?obj_id=1835","callNumber":"D 2554","year":"2554","semester":"1","examType":"Final"},{"index":"1442","subjectCode":"CSS 223","subjectName":"Data Structures 28 ก.ค. 2553","link":"https://dl.lib.kmutt.ac.th/repository/loadfile.php?obj_id=2684","callNumber":"D 2553","year":"2553","semester":"1","examType":"Mid-Term"},{"index":"1443","subjectCode":"CSS 223","subjectName":"Data Structures 22 ก.ค.2552","link":"https://dl.lib.kmutt.ac.th/repository/loadfile.php?obj_id=2750","callNumber":"D 2552","year":"2552","semester":"1","examType":"Mid-Term"},{"index":"1444","subjectCode":"CSS 223","subjectName":"Data Structures  30 ก.ย.2552","link":"https://dl.lib.kmutt.ac.th/repository/loadfile.php?obj_id=3125","callNumber":"D 2552","year":"2552","semester":"1","examType":"Final"},{"index":"1445","subjectCode":"CSS 223","subjectName":"Data Structures  6 ต.ค.2551","link":"https://dl.lib.kmutt.ac.th/repository/loadfile.php?obj_id=3726","callNumber":"D 2551","year":"2551","semester":"1","examType":"Final"},{"index":"1446","subjectCode":"CSS 223","subjectName":"Data Structures  28 ก.ค.2551","link":"https://dl.lib.kmutt.ac.th/repository/loadfile.php?obj_id=3409","callNumber":"D 2551","year":"2551","semester":"1","examType":"Mid-Term"},{"index":"1447","subjectCode":"CSS 223","subjectName":"Data Structures","link":"https://dl.lib.kmutt.ac.th/repository/loadfile.php?obj_id=3379","callNumber":"D 2550","year":"2550","semester":"1","examType":"Mid-Term"},{"index":"1448","subjectCode":"CSS 223","subjectName":"Data Structures  11 ต.ค.2550","link":"https://dl.lib.kmutt.ac.th/repository/loadfile.php?obj_id=3708","callNumber":"D 2550","year":"2550","semester":"1","examType":"Final"},{"index":"1449","subjectCode":"CSS 223","subjectName":"Data Structures","link":null,"callNumber":"D 2548","year":"2548","semester":"1","examType":"Mid-Term,Final"},{"index":"1450","subjectCode":"CSS 223","subjectName":"Data Structures","link":null,"callNumber":"D 2547","year":"2547","semester":"1","examType":"Mid-Term,Final"}]