[{"index":"6191","subjectCode":"MEE 211","subjectName":"Engineering Mechanics(Inter,Mechanical Engineering)","link":"https://dl.lib.kmutt.ac.th/repository/loadfile.php?obj_id=1039","callNumber":"EN-EX 2557","year":"2557","semester":"1","examType":"Final"},{"index":"6192","subjectCode":"MEE 211","subjectName":"Engineering Mechanics(Inter,Mechanical Engineering)","link":"https://dl.lib.kmutt.ac.th/repository/loadfile.php?obj_id=1196","callNumber":"EN-EX 2557","year":"2557","semester":"1","examType":"Mid-Term"},{"index":"6193","subjectCode":"MEE 211","subjectName":"Engineering Mechanics วิศกรรมเครื่องกล  /8 May 2014","link":"https://dl.lib.kmutt.ac.th/repository/loadfile.php?obj_id=1587","callNumber":"EN 2556","year":"2556","semester":"2","examType":"Final"},{"index":"6194","subjectCode":"MEE 211","subjectName":"Engineering Mechanics วิศกรรมเครื่องกล (Aj.Ekachai, Dr. Chawin, Dr.Pattaramon","link":"https://dl.lib.kmutt.ac.th/repository/loadfile.php?obj_id=230","callNumber":"EN-EX 2555","year":"2555","semester":"1","examType":"Final"},{"index":"6195","subjectCode":"MEE 211","subjectName":"Engineering Mechanics วิศกรรมเครื่องกล (Aj.Ekachai, Dr. Chawin, Dr.Pattaramon","link":"https://dl.lib.kmutt.ac.th/repository/loadfile.php?obj_id=2083","callNumber":"EN-EX 2554","year":"2554","semester":"1","examType":"Mid-Term"},{"index":"6196","subjectCode":"MEE 211","subjectName":"Engineering Mechanics (วิศกรรมเครื่องกล )/28 Sep 2011","link":"https://dl.lib.kmutt.ac.th/repository/loadfile.php?obj_id=1898","callNumber":"EN-EX 2554","year":"2554","semester":"1","examType":"Final"},{"index":"6197","subjectCode":"MEE 211","subjectName":"Engineering Mechanics I ( Statics) 21 July 2010","link":"https://dl.lib.kmutt.ac.th/repository/loadfile.php?obj_id=2892","callNumber":"EN 2553","year":"2553","semester":"1","examType":"Mid-Term"},{"index":"6198","subjectCode":"MEE 211","subjectName":"Engineering  29 Sep 2010","link":"https://dl.lib.kmutt.ac.th/repository/loadfile.php?obj_id=4039","callNumber":"EN 2553","year":"2553","semester":"1","examType":"Final"},{"index":"6199","subjectCode":"MEE 211","subjectName":"Engineering Mechanics วิศกรรมเครื่องกล (Aj.Ekachai, Dr. Chawin, Dr.Pattaramon)","link":null,"callNumber":"EN-EX 2552","year":"2552","semester":"1","examType":"Mid-Term"},{"index":"6200","subjectCode":"MEE 211","subjectName":"Engineering Mechanics 22 July 2009","link":"https://dl.lib.kmutt.ac.th/repository/loadfile.php?obj_id=2948","callNumber":"","year":"2552","semester":"1","examType":"Mid-Term"}]