[{"index":"1291","subjectCode":"CPE 458","subjectName":"Digital Commerce_5/18/2016","link":"https://dl.lib.kmutt.ac.th/repository/loadfile.php?obj_id=2542","callNumber":"","year":"2558","semester":"2","examType":"Final"},{"index":"1292","subjectCode":"CPE 458","subjectName":"Digital Commerce","link":"https://dl.lib.kmutt.ac.th/repository/loadfile.php?obj_id=760","callNumber":"","year":"2557","semester":"2","examType":"Mid-Term"},{"index":"1293","subjectCode":"CPE 461","subjectName":"Advanced Electronic Design 28 July 2009","link":"https://dl.lib.kmutt.ac.th/repository/loadfile.php?obj_id=2744","callNumber":"A-B 2552","year":"2552","semester":"1","examType":"Mid-Term"},{"index":"1294","subjectCode":"CPE 461","subjectName":"Advanced Electronic Design","link":null,"callNumber":"A-B 2551","year":"2551","semester":"1","examType":"Final"},{"index":"1295","subjectCode":"CPE 461","subjectName":"Advanced Electronic Design  29 July 2008","link":"https://dl.lib.kmutt.ac.th/repository/loadfile.php?obj_id=3400","callNumber":"A-B 2551","year":"2551","semester":"1","examType":"Mid-Term"},{"index":"1296","subjectCode":"CPE 462","subjectName":"Analog VLSI for Signal Processing","link":null,"callNumber":"A-B 2547","year":"2547","semester":"1","examType":"Mid-Term"},{"index":"1297","subjectCode":"CPE 462","subjectName":"Analog VLSI for Signal Processing I","link":null,"callNumber":"A-B 2544","year":"2544","semester":"1","examType":"Mid-Term"},{"index":"1298","subjectCode":"CPE 462","subjectName":"Network Synthesis for Analog VLSI","link":null,"callNumber":"N-O 2543","year":"2543","semester":"1","examType":"Mid-Term"},{"index":"1299","subjectCode":"CPE 463","subjectName":"Analog V L S I for Signal Processing I  CPE 4 A-D  29 July 2008","link":"https://dl.lib.kmutt.ac.th/repository/loadfile.php?obj_id=3401","callNumber":"A-B 2551","year":"2551","semester":"1","examType":"Mid-Term"},{"index":"1300","subjectCode":"CPE 463","subjectName":"Analog VLSI for Signal Processing I","link":null,"callNumber":"A-B 2548","year":"2548","semester":"1","examType":"Final"}]