[{"index":"8681","subjectCode":"PRE 394","subjectName":"Industrial Safety","link":null,"callNumber":"I 2546","year":"2546","semester":"2","examType":"Mid-Term"},{"index":"8682","subjectCode":"PRE 427","subjectName":"Radiogrphic Testing","link":null,"callNumber":"Q-R 2546","year":"2546","semester":"1","examType":"Mid-Term,Final"},{"index":"8683","subjectCode":"PRE 427","subjectName":"Radiograghic Testing","link":null,"callNumber":"Q-R 2545","year":"2545","semester":"1,2","examType":"Mid-Term,Final"},{"index":"8684","subjectCode":"PRE 427","subjectName":"Radiograghic Testing","link":null,"callNumber":"Q-R 2544","year":"2544","semester":"2","examType":"Final"},{"index":"8685","subjectCode":"PRE 427","subjectName":"Radiograghic Testing","link":null,"callNumber":"Q-R 2544","year":"2544","semester":"1","examType":"Final"},{"index":"8686","subjectCode":"PRE 428","subjectName":"Surface Method Testing","link":null,"callNumber":"ST-SY 2547","year":"2547","semester":"2","examType":"Mid-Term"},{"index":"8687","subjectCode":"PRE 428","subjectName":"Surface Method Testing","link":null,"callNumber":"S 2546","year":"2546","semester":"2","examType":"Mid-Term"},{"index":"8688","subjectCode":"PRE 429","subjectName":"Ultrasonic Testing","link":null,"callNumber":"T-W 2546","year":"2546","semester":"1","examType":"Mid-Term,Final"},{"index":"8689","subjectCode":"PRE 429","subjectName":"Ultrasonic Testing","link":null,"callNumber":"T-W 2545","year":"2545","semester":"1","examType":"Mid-Term"},{"index":"8690","subjectCode":"PRE 445","subjectName":"Computer Aided Manufacturing","link":null,"callNumber":"CN-CU- 2547","year":"2547","semester":"1","examType":"Final"}]